alas_tools/__init__.py
alas_tools/clients/__init__.py
alas_tools/clients/cn_admin/__init__.py
alas_tools/clients/cn_admin/client_b2b_service.py
alas_tools/clients/cn_admin/corenet_api_client.py
alas_tools/clients/cn_admin/integradial_config_service.py
alas_tools/clients/cn_admin/order_status_service.py
alas_tools/clients/cn_admin/service_api_client.py
alas_tools/clients/delivery/__init__.py
alas_tools/clients/delivery/b2c.py
alas_tools/clients/delivery/delivery_order.py
alas_tools/clients/integration/__init__.py
alas_tools/clients/integration/device_magic.py
alas_tools/clients/integration/integration_api.py
alas_tools/clients/integration/intergradial.py
alas_tools/clients/integration/shipper.py
alas_tools/clients/integration/whatsapp.py
alas_tools/clients/management/__init__.py
alas_tools/clients/management/barcode.py
alas_tools/clients/management/configuration.py
alas_tools/clients/management/contact.py
alas_tools/clients/management/cross_docking.py
alas_tools/clients/management/delivery_entity.py
alas_tools/clients/management/distribution_zone.py
alas_tools/clients/management/employee.py
alas_tools/clients/management/feature.py
alas_tools/clients/management/geographic_coverage.py
alas_tools/clients/management/geographic_coverage_active.py
alas_tools/clients/management/maintenance.py
alas_tools/clients/management/notification.py
alas_tools/clients/management/package_template.py
alas_tools/clients/management/packaging.py
alas_tools/clients/management/product_template.py
alas_tools/clients/management/resource.py
alas_tools/clients/management/role.py
alas_tools/clients/management/roles_group.py
alas_tools/clients/management/service_level.py
alas_tools/clients/management/shelf.py
alas_tools/clients/management/source_location.py
alas_tools/clients/management/task.py
alas_tools/clients/management/user.py
alas_tools/clients/management/vehicle.py
alas_tools/clients/management/workflow.py
alas_tools/common/__init__.py
alas_tools/common/configurable_base.py
alas_tools-0.55.dist-info/METADATA
alas_tools-0.55.dist-info/WHEEL
alas_tools-0.55.dist-info/top_level.txt
alas_tools-0.55.dist-info/RECORD
