Metadata-Version: 2.1
Name: alas-tools
Version: 0.55
Summary: API tools for Alas.Ce0 project
Home-page: https://github.com/pypa/alas-tools
Author: Carlos Serrano
Author-email: cserrano@alasxpress.com
License: MIT
Keywords: alas-tools api client development
Platform: UNKNOWN
Classifier: Development Status :: 3 - Alpha
Classifier: Intended Audience :: Developers
Classifier: Topic :: Software Development :: Build Tools
Classifier: License :: OSI Approved :: MIT License
Classifier: Programming Language :: Python :: 2.7
Requires-Dist: enum34
Requires-Dist: httplib2
Requires-Dist: pendulum
Requires-Dist: alas-ce0-client
Provides-Extra: dev
Requires-Dist: check-manifest ; extra == 'dev'
Provides-Extra: test
Requires-Dist: coverage ; extra == 'test'
